{
    "config_ndims_5_ncop_3_nsamples_10000_niter_10000": {
        "fn": {
            "name": "fn",
            "class_name": "GMetrics.FNMetric",
            "kwargs": {},
            "test_config": {
                "_niter": 10000,
                "_batch_size_test": 10000,
                "_batch_size_gen": 1000,
                "_small_sample_threshold": 10000000,
                "_dtype_input": "float64",
                "_seed": 0,
                "_use_tf": true,
                "_mirror_strategy": false,
                "_verbose": true,
                "_is_symb_1": true,
                "_ndims_1": 5,
                "_nsamples_1": 0,
                "_is_symb_2": true,
                "_ndims_2": 5,
                "_nsamples_2": 0,
                "_dtype": "float64",
                "_ndims": 5,
                "_nsamples": 100000000,
                "_small_sample": false
            },
            "null_file": "../results/analysis_10K/Null_5D_FN.json",
            "thresholds": [
                [
                    0.68,
                    [
                        6800,
                        3199
                    ],
                    0.7179960706493972
                ],
                [
                    0.95,
                    [
                        9500,
                        500
                    ],
                    1.201933747163374
                ],
                [
                    0.99,
                    [
                        9900,
                        100
                    ],
                    1.5292055424498905
                ]
            ],
            "result_key": "metric_list",
            "scale_func": "callable: <lambda>",
            "scale_func_string": "lambda ns, ndims: np.sqrt(ns)/ndims"
        }
    }
}